{
  "project_info": {
    "project_number": "641725584739",
    "firebase_url": "https://getx-todo-97713-default-rtdb.firebaseio.com",
    "project_id": "getx-todo-97713",
    "storage_bucket": "getx-todo-97713.appspot.com"
  },
  "client": [
    {
      "client_info": {
        "mobilesdk_app_id": "1:641725584739:android:29c0ea37648dd18cb4ef56",
        "android_client_info": {
          "package_name": "com.seongwoo.firebase_todo_app"
        }
      },
      "oauth_client": [
        {
          "client_id": "641725584739-gjilbrl8f6oennj7ssnbr7etl8fpfha1.apps.googleusercontent.com",
          "client_type": 1,
          "android_info": {
            "package_name": "com.seongwoo.firebase_todo_app",
            "certificate_hash": "025641198198a71b1427249fdf1ab66515087684"
          }
        },
        {
          "client_id": "641725584739-dtjhnbu9392r8oldmkqof7u2di2httve.apps.googleusercontent.com",
          "client_type": 3
        }
      ],
      "api_key": [
        {
          "current_key": "AIzaSyCFybaLHpOsWIrt-L4O16GX2knFB7UnRbI"
        }
      ],
      "services": {
        "appinvite_service": {
          "other_platform_oauth_client": [
            {
              "client_id": "641725584739-dtjhnbu9392r8oldmkqof7u2di2httve.apps.googleusercontent.com",
              "client_type": 3
            }
          ]
        }
      }
    }
  ],
  "configuration_version": "1"
}